[{"authors":["admin"],"categories":null,"content":"Paulo Aragao is a Phd student at the Technische Universität Kaiserslautern. His research interests include wireless networks, with special focus on channel sensing and channel hopping within ad-hoch networks.\n","date":-62135596800,"expirydate":-62135596800,"kind":"taxonomy","lang":"en","lastmod":-62135596800,"objectID":"2525497d367e79493fd32b198b28f040","permalink":"/authors/admin/","publishdate":"0001-01-01T00:00:00Z","relpermalink":"/authors/admin/","section":"authors","summary":"Paulo Aragao is a Phd student at the Technische Universität Kaiserslautern. His research interests include wireless networks, with special focus on channel sensing and channel hopping within ad-hoch networks.","tags":null,"title":"Paulo Aragao","type":"authors"}]